<?xml version="1.0" encoding="UTF-8"?>
<!DOCTYPE tiles-definitions PUBLIC "-//Apache Software Foundation//DTD Tiles Configuration 2.1//EN" "http://tiles.apache.org/dtds/tiles-config_2_1.dtd">

<tiles-definitions>
    
    <!-- Login Template -->
    <definition name="login" template="/layout/login-template.jsp">
        <put-attribute name="title" value="Log Ind" />
        <put-attribute name="content" value="/views/public/login.jsp" />
    </definition>
    
    <!-- Default Template -->
    <definition name="default-template" template="/layout/default-template.jsp">
        <put-attribute name="title" value="" />
        <put-attribute name="content" value="" />
        <put-attribute name="page" value="" />
    </definition>
    
    <!-- Home View -->
    <definition name="home" extends="default-template">
        <put-attribute name="title" value="Movstream" />
        <put-attribute name="content" value="/views/private/home.jsp" />
        <put-attribute name="page" value="home" />
    </definition>
    
    <!-- Season Show Episodes View -->
    <definition name="showepisodes" extends="default-template">
        <put-attribute name="title" value="movstream" />
        <put-attribute name="content" value="/views/private/showepisodes.jsp" />
        <put-attribute name="page" value="season" />
    </definition>
    
    <!-- Show movie View -->
    <definition name="showmovie" extends="default-template">
        <put-attribute name="title" value="movstream" />
        <put-attribute name="content" value="/views/private/showmovie.jsp" />
        <put-attribute name="page" value="movie" />
    </definition>
    
    <!-- Show movie by genre view -->
    <definition name="showmoviesbygenre" extends="default-template">
        <put-attribute name="title" value="movstream" />
        <put-attribute name="content" value="/views/private/showmoviesbygenre.jsp" />
        <put-attribute name="page" value="genre" />
    </definition>
    
</tiles-definitions>